pydockerutils/__init__.py
pydockerutils/configs.py
pydockerutils/main.py
pydockerutils/static.py
pydockerutils/utils.py
pydockerutils-0.0.6.dist-info/LICENSE
pydockerutils-0.0.6.dist-info/METADATA
pydockerutils-0.0.6.dist-info/WHEEL
pydockerutils-0.0.6.dist-info/entry_points.txt
pydockerutils-0.0.6.dist-info/top_level.txt
pydockerutils-0.0.6.dist-info/RECORD
